LICENSE
MANIFEST.in
Makefile
README
TODO
setup.py
ballotbox/__init__.py
ballotbox/ballot.py
ballotbox/criteria.py
ballotbox/iballot.py
ballotbox/meta.py
ballotbox/proxy.py
ballotbox/random.py
ballotbox.egg-info/PKG-INFO
ballotbox.egg-info/SOURCES.txt
ballotbox.egg-info/dependency_links.txt
ballotbox.egg-info/top_level.txt
ballotbox/multiwinner/__init__.py
ballotbox/multiwinner/majoritarian.py
ballotbox/multiwinner/proportional.py
ballotbox/multiwinner/semiproportional.py
ballotbox/singlewinner/__init__.py
ballotbox/singlewinner/plurality.py
ballotbox/singlewinner/rated.py
ballotbox/singlewinner/simple.py
ballotbox/singlewinner/preferential/__init__.py
ballotbox/singlewinner/preferential/base.py
ballotbox/singlewinner/preferential/borda.py
ballotbox/singlewinner/preferential/condorcet.py
ballotbox/singlewinner/preferential/minimax.py
ballotbox/singlewinner/preferential/other.py
ballotbox/testing/__init__.py
ballotbox/testing/suite.py
ballotbox/tests/__init__.py
ballotbox/util/__init__.py
ballotbox/util/dist.py
docs/HISTORY.txt
docs/INSTALL.txt
docs/LICENSE.txt
docs/PRELUDE.txt
docs/README.txt
docs/TODO.txt
docs/USAGE.txt
docs/api/API.txt
docs/api/BALLOT.txt
docs/api/INTERFACES.txt
docs/api/MULTIWINNER.txt
docs/api/OTHER.txt
docs/api/SINGLEWINNER.txt
docs/html/_sources/index.txt
docs/html/_sources/docs/API.txt
docs/html/_sources/docs/HISTORY.txt
docs/html/_sources/docs/INSTALL.txt
docs/html/_sources/docs/LICENSE.txt
docs/html/_sources/docs/PRELUDE.txt
docs/html/_sources/docs/README.txt
docs/html/_sources/docs/TODO.txt
docs/html/_sources/docs/USAGE.txt
docs/html/_sources/docs/VOTINGMETHODS.txt
docs/html/_sources/docs/api/API.txt
docs/html/_sources/docs/api/BALLOT.txt
docs/html/_sources/docs/api/INTERFACES.txt
docs/html/_sources/docs/api/MULTIWINNER.txt
docs/html/_sources/docs/api/OTHER.txt
docs/html/_sources/docs/api/SINGLEWINNER.txt
docs/html/_sources/docs/methods/VOTINGMETHODS.txt
docs/html/_sources/docs/methods/heading.txt
docs/html/_sources/docs/methods/multiwinner/majoritarian.txt
docs/html/_sources/docs/methods/multiwinner/proportional.txt
