Metadata-Version: 1.0
Name: ballotbox
Version: 0.1
Summary: A Python library for voting algorithms.
Home-page: http://launchpad.net/ballotbox
Author: Duncan McGreggor
Author-email: oubiwann@gmail.com
License: LGPLv3
Platform: UNKNOWN
Classifier: Development Status :: 4 - Beta
Classifier: Intended Audience :: Developers
Classifier: Programming Language :: Python
